smartworld/__init__.py
smartworld/__version__.py
smartworld/core.py
smartworld/scripts/__init__.py
smartworld/scripts/batch_rename.py
smartworld/scripts/mapping.py
smartworld/scripts/resource_monitor.py
smartworld/scripts/switch_gateway.py
smartworld/scripts/sync_repo.py
smartworld/scripts/test.py
smartworld-0.2.3.dist-info/LICENSE
smartworld-0.2.3.dist-info/METADATA
smartworld-0.2.3.dist-info/WHEEL
smartworld-0.2.3.dist-info/entry_points.txt
smartworld-0.2.3.dist-info/top_level.txt
smartworld-0.2.3.dist-info/RECORD
