Metadata-Version: 2.1
Name: smartworld
Version: 0.2.3
Summary: Tools Collection of Smartworld
Home-page: 
Author: Frank Xu
Author-email: frank.xu@cloudminds.com
License: MIT
Classifier: License :: OSI Approved :: MIT License
Classifier: Programming Language :: Python
Classifier: Programming Language :: Python :: 3
Classifier: Programming Language :: Python :: 3.6
Classifier: Programming Language :: Python :: Implementation :: CPython
Classifier: Programming Language :: Python :: Implementation :: PyPy
Requires-Python: >=3.6.0
License-File: LICENSE
Requires-Dist: click
Requires-Dist: colorama
Requires-Dist: gitpython
Requires-Dist: tqdm
